tadoasync/__init__.py
tadoasync/const.py
tadoasync/exceptions.py
tadoasync/models.py
tadoasync/py.typed
tadoasync/tadoasync.py
tadoasync-0.2.2.dist-info/METADATA
tadoasync-0.2.2.dist-info/WHEEL
tadoasync-0.2.2.dist-info/licenses/LICENSE.md
tadoasync-0.2.2.dist-info/RECORD
